twitchoglc/__init__.py
twitchoglc/bezier.py
twitchoglc/brushmodel.py
twitchoglc/brushviewer.py
twitchoglc/bsp.py
twitchoglc/downloader.py
twitchoglc/maprender.py
twitchoglc/pk3.py
twitchoglc/shaderparser.py
twitchoglc/viewer.py
twitchoglc-2.0.1.dist-info/DESCRIPTION.rst
twitchoglc-2.0.1.dist-info/METADATA
twitchoglc-2.0.1.dist-info/RECORD
twitchoglc-2.0.1.dist-info/WHEEL
twitchoglc-2.0.1.dist-info/entry_points.txt
twitchoglc-2.0.1.dist-info/metadata.json
twitchoglc-2.0.1.dist-info/top_level.txt
